AUTHORS.rst
HISTORY.rst
LICENSE
MANIFEST.in
README.rst
setup.cfg
setup.py
MCres/FakeSampler.py
MCres/MCres.py
MCres/__init__.py
MCres/_core.py
MCres/_version.py
MCres/load.py
MCres.egg-info/PKG-INFO
MCres.egg-info/SOURCES.txt
MCres.egg-info/dependency_links.txt
MCres.egg-info/requires.txt
MCres.egg-info/top_level.txt