Metadata-Version: 1.1
Name: MCres
Version: 0.5.8
Summary: Provides simple filtering and visualization tools for Monte-Carlo simulation data
Home-page: https://github.com/ceyzeriat/MCres/
Author: Guillaume Schworer
Author-email: guillaume.schworer@obspm.fr
License: GNU General Public License v3 or later (GPLv3+)
Download-URL: https://github.com/ceyzeriat/MCres/tree/master/dist
Keywords: emcee,processing,data,big data,corner,cornerplot,triangle,plot
Platform: UNKNOWN
Classifier: Development Status :: 4 - Beta
Classifier: Environment :: Console
Classifier: Intended Audience :: Education
Classifier: Intended Audience :: Science/Research
Classifier: License :: OSI Approved :: GNU General Public License v3 or later (GPLv3+)
Classifier: Operating System :: OS Independent
Classifier: Programming Language :: Python
Classifier: Topic :: Documentation :: Sphinx
Classifier: Topic :: Scientific/Engineering :: Physics
